prsync/__init__.py
prsync/main.py
prsync/gui/__init__.py
prsync/gui/screen.py
prsync/gui/screen_api.py
prsync/gui/screen_validations.py
prsync/gui/screen_vars.py
prsync/network/__init__.py
prsync/network/ssh/__init__.py
prsync/network/ssh/connection.py
prsync/network/ssh/ssh_client.py
prsync/network/ssh/commands/__init__.py
prsync/network/ssh/commands/routing.py
prsync/network/ssh/commands/rsync.py
test/__init__.py
test/test_gui.py
prsync-0.0.11.dist-info/LICENSE
prsync-0.0.11.dist-info/METADATA
prsync-0.0.11.dist-info/WHEEL
prsync-0.0.11.dist-info/dependency_links.txt
prsync-0.0.11.dist-info/entry_points.txt
prsync-0.0.11.dist-info/top_level.txt
prsync-0.0.11.dist-info/RECORD
