Metadata-Version: 2.1
Name: prsync
Version: 0.0.11
Summary: a GUI for rsync (linux servers)
Home-page: https://github.com/itay-bardugo/prsync/
Author: Itay Bardugo
Author-email: itaybardugo91@gmail.com
License: UNKNOWN
Platform: UNKNOWN
Classifier: Programming Language :: Python :: 3
Classifier: License :: OSI Approved :: MIT License
Classifier: Operating System :: OS Independent
Requires-Dist: paramiko
